http_sfv/__init__.py
http_sfv/__main__.py
http_sfv/boolean.py
http_sfv/byteseq.py
http_sfv/date.py
http_sfv/decimal.py
http_sfv/dictionary.py
http_sfv/display_string.py
http_sfv/integer.py
http_sfv/item.py
http_sfv/list.py
http_sfv/py.typed
http_sfv/string.py
http_sfv/token.py
http_sfv/types.py
http_sfv/util.py
http_sfv/util_json.py
http_sfv-0.9.9.dist-info/LICENCE.md
http_sfv-0.9.9.dist-info/METADATA
http_sfv-0.9.9.dist-info/WHEEL
http_sfv-0.9.9.dist-info/top_level.txt
http_sfv-0.9.9.dist-info/RECORD
