Metadata-Version: 2.1
Name: http_sfv
Version: 0.9.9
Summary: Parse and serialise HTTP Structured Field Values
Home-page: https://github.com/mnot/http_sfv
Author: Mark Nottingham
Author-email: mnot@mnot.net
Project-URL: Bug Tracker, https://github.com/mnot/http_sfv/issues
Classifier: Development Status :: 7 - Inactive
Classifier: Intended Audience :: Developers
Classifier: License :: OSI Approved :: MIT License
Classifier: Programming Language :: Python
Classifier: Programming Language :: Python :: 3.8
Classifier: Operating System :: POSIX
Classifier: Topic :: Internet :: WWW/HTTP
Classifier: Topic :: Software Development :: Libraries :: Python Modules
Requires-Python: >=3.8
License-File: LICENCE.md
Requires-Dist: typing_extensions
Provides-Extra: dev
Requires-Dist: mypy; extra == "dev"
Requires-Dist: black; extra == "dev"
